prep_flow/__init__.py
prep_flow/base.py
prep_flow/decorators.py
prep_flow/errors.py
prep_flow/expressions.py
prep_flow/validator.py
samples/01_simple_usage.ipynb
tests/data/test_parse_data.xlsx
tests/data/test_validate_sheet_name.xlsx
prep_flow-0.1.2.dist-info/LICENSE
prep_flow-0.1.2.dist-info/METADATA
prep_flow-0.1.2.dist-info/WHEEL
prep_flow-0.1.2.dist-info/top_level.txt
prep_flow-0.1.2.dist-info/RECORD
