Metadata-Version: 2.1
Name: prep-flow
Version: 0.1.2
Summary: prep-flow: Data preprocessing framework with type validation for data scientists.
Author-email: Tomohiko Kato <s.tk1619@gmail.com>
License: MIT License
Classifier: Programming Language :: Python :: 3
Requires-Python: >=3.10
License-File: LICENSE
Requires-Dist: numpy >=1.20.3
Requires-Dist: pandas >=1.2.4
Requires-Dist: openpyxl >=3.0.0
Requires-Dist: pydantic >=2.0.0
Provides-Extra: dev
Requires-Dist: pytest ; extra == 'dev'
Requires-Dist: flake8 ; extra == 'dev'
Requires-Dist: black ; extra == 'dev'
Requires-Dist: isort ; extra == 'dev'
Requires-Dist: jupyter ; extra == 'dev'
